README.md
setup.py
DRMAAtic_lib.egg-info/PKG-INFO
DRMAAtic_lib.egg-info/SOURCES.txt
DRMAAtic_lib.egg-info/dependency_links.txt
DRMAAtic_lib.egg-info/requires.txt
DRMAAtic_lib.egg-info/top_level.txt
drmaatic_lib/__init__.py
drmaatic_lib/job.py
drmaatic_lib/manage.py
drmaatic_lib/session.py
drmaatic_lib/utils.py
drmaatic_lib/sge/__init__.py
drmaatic_lib/sge/job.py
drmaatic_lib/slurm/__init__.py
drmaatic_lib/slurm/job.py