Metadata-Version: 2.1
Name: DRMAAtic-lib
Version: 1.0.8
Summary: DRMAA interface for Slurm/SGE DRMs @ BioComputingUP lab
Author: Alessio Del Conte
Author-email: alessio.delconte@phd.unipd.it
License: MIT
Classifier: Programming Language :: Python :: 3
Classifier: License :: OSI Approved :: MIT License
Classifier: Operating System :: Unix
Requires-Python: >=3.6
Requires-Dist: drmaa
